tas_tools/__init__.py
tas_tools/utils/__init__.py
tas_tools/utils/station_maintenance_utils.py
tas_tools-0.0.0.0.dist-info/METADATA
tas_tools-0.0.0.0.dist-info/WHEEL
tas_tools-0.0.0.0.dist-info/top_level.txt
tas_tools-0.0.0.0.dist-info/RECORD
